{
  "project_info": {
    "project_number": "401660921517",
    "project_id": "book-trackerq",
    "storage_bucket": "book-trackerq.appspot.com"
  },
  "client": [
    {
      "client_info": {
        "mobilesdk_app_id": "1:401660921517:android:8158b81e8c1f431d8aa824",
        "android_client_info": {
          "package_name": "com.bookstracker"
        }
      },
      "oauth_client": [
        {
          "client_id": "401660921517-0bncdfj7ahbl7h650vs4b1mhoepakst5.apps.googleusercontent.com",
          "client_type": 3
        }
      ],
      "api_key": [
        {
          "current_key": "AIzaSyBpU-vytfHaWLwhG2oKEPONIsIAWGsDMMo"
        }
      ],
      "services": {
        "appinvite_service": {
          "other_platform_oauth_client": [
            {
              "client_id": "401660921517-0bncdfj7ahbl7h650vs4b1mhoepakst5.apps.googleusercontent.com",
              "client_type": 3
            }
          ]
        }
      }
    }
  ],
  "configuration_version": "1"
}